{"pipelineKey":"ee5e88f9ea1b484ebbca401f6baaac4e","name":"Pipeline_8701","description":"","definition":"{\"workerLimit\":4,\"tasks\":[{\"children\":[\"DataflowUJOZT\",\"DataflowUJOZTJWHlG\",\"DataflowUJOZTvJsCw\",\"DataflowUJOZTCt57a\",\"DataflowUJOZTL2tl5\",\"DataflowUJOZTgwb1h\"],\"iteratee\":{},\"id\":\"Terminator\",\"type\":\"Terminator\"},{\"parent\":[\"Terminator\"],\"stopOnTaskFailure\":\"N\",\"dfName\":\"Dataflow_1635\",\"stopDependentTasks\":\"N\",\"label\":\"Data\",\"type\":\"runDataFlow\",\"userId\":\"48\",\"dfKey\":\"a8bce56e-ba5e-462a-80e3-0d8cf961079b\",\"livyServer\":\"146_livy\",\"children\":[],\"iteratee\":{},\"name\":\"Dataflow_1635\",\"id\":\"DataflowUJOZT\",\"parameters\":\"limit_rows:limit 1000\"},{\"parent\":[\"Terminator\"],\"stopOnTaskFailure\":\"N\",\"dfName\":\"Dataflow_1635\",\"stopDependentTasks\":\"N\",\"label\":\"Data\",\"type\":\"runDataFlow\",\"userId\":\"48\",\"dfKey\":\"a8bce56e-ba5e-462a-80e3-0d8cf961079b\",\"livyServer\":\"146_livy\",\"children\":[],\"iteratee\":{},\"name\":\"Dataflow_1635\",\"id\":\"DataflowUJOZTJWHlG\",\"parameters\":\"limit_rows:limit 1000\"},{\"parent\":[\"Terminator\"],\"stopOnTaskFailure\":\"N\",\"dfName\":\"Dataflow_1635\",\"stopDependentTasks\":\"N\",\"label\":\"Data\",\"type\":\"runDataFlow\",\"userId\":\"48\",\"dfKey\":\"a8bce56e-ba5e-462a-80e3-0d8cf961079b\",\"livyServer\":\"146_livy\",\"children\":[],\"iteratee\":{},\"name\":\"Dataflow_1635\",\"id\":\"DataflowUJOZTvJsCw\",\"parameters\":\"limit_rows:limit 1000\"},{\"parent\":[\"Terminator\"],\"stopOnTaskFailure\":\"N\",\"dfName\":\"Dataflow_1635\",\"stopDependentTasks\":\"N\",\"label\":\"Data\",\"type\":\"runDataFlow\",\"userId\":\"48\",\"dfKey\":\"a8bce56e-ba5e-462a-80e3-0d8cf961079b\",\"livyServer\":\"146_livy\",\"children\":[],\"iteratee\":{},\"name\":\"Dataflow_1635\",\"id\":\"DataflowUJOZTCt57a\",\"parameters\":\"limit_rows:limit 1000\"},{\"parent\":[\"Terminator\"],\"stopOnTaskFailure\":\"N\",\"dfName\":\"Dataflow_1635\",\"stopDependentTasks\":\"N\",\"label\":\"Data\",\"type\":\"runDataFlow\",\"userId\":\"48\",\"dfKey\":\"a8bce56e-ba5e-462a-80e3-0d8cf961079b\",\"livyServer\":\"146_livy\",\"children\":[],\"iteratee\":{},\"name\":\"Dataflow_1635\",\"id\":\"DataflowUJOZTL2tl5\",\"parameters\":\"limit_rows:limit 1000\"},{\"parent\":[\"Terminator\"],\"stopOnTaskFailure\":\"N\",\"dfName\":\"Dataflow_1635\",\"stopDependentTasks\":\"N\",\"label\":\"Data\",\"type\":\"runDataFlow\",\"userId\":\"48\",\"dfKey\":\"a8bce56e-ba5e-462a-80e3-0d8cf961079b\",\"livyServer\":\"146_livy\",\"children\":[],\"iteratee\":{},\"name\":\"Dataflow_1635\",\"id\":\"DataflowUJOZTgwb1h\",\"parameters\":\"limit_rows:limit 1000\"}]}"}