{"pipelineKey":"fdd37c0b7bd24bc891cc9f8f9d40c799","name":"Pipeline_DB","description":"","definition":"{\"tasks\":[{\"children\":[\"DB FlowHbeci\"],\"iteratee\":{},\"id\":\"Terminator\",\"type\":\"Terminator\"},{\"parent\":[\"Terminator\"],\"stopOnTaskFailure\":\"N\",\"label\":\"testcase\",\"dfName\":\"DB Flow_Piper\",\"stopDependentTasks\":\"N\",\"type\":\"testcase\",\"userId\":\"48\",\"dfKey\":\"515c92bf-3bd6-4939-8d3b-cd79ece18928\",\"children\":[\"DatabrickscTxhf\"],\"iteratee\":{},\"name\":\"DB Flow_Piper\",\"id\":\"DB FlowHbeci\",\"parameters\":\"limit_rows:limit 1000\"},{\"parent\":[\"DB FlowHbeci\"],\"livyServer\":\"${AzureStart}\",\"children\":[\"DatabricksyHSJP\",\"DataflowQJvog\"],\"iteratee\":{},\"name\":\"AzureStart\",\"stackName\":\"check\",\"action\":\"create\",\"id\":\"DatabrickscTxhf\",\"label\":\"AzureCluster\",\"type\":\"AzureCluster\",\"templateId\":\"3\",\"userId\":\"48\"},{\"parent\":[\"DatabrickscTxhf\"],\"livyServer\":\"${AzureStart}\",\"children\":[],\"iteratee\":{},\"name\":\"AzureStop\",\"action\":\"stop\",\"id\":\"DatabricksyHSJP\",\"label\":\"AzureCluster\",\"type\":\"AzureCluster\",\"userId\":\"48\"},{\"parent\":[\"DatabrickscTxhf\"],\"stopOnTaskFailure\":\"N\",\"dfName\":\"AB 13 F\",\"stopDependentTasks\":\"N\",\"label\":\"Data\",\"type\":\"runDataFlow\",\"userId\":\"48\",\"dfKey\":\"d7bb9281-0324-41f0-b797-9669d52477e7\",\"livyServer\":\"${AzureStart}\",\"children\":[],\"iteratee\":{},\"name\":\"AB 13 F\",\"id\":\"DataflowQJvog\",\"parameters\":\"limit_rows:limit 1000\"}]}"}