{"pipelineKey":"09b839b7-554c-40ba-8ca2-a8fb47da9694","name":"Pipeline_1684_125","description":"","definition":"{\"workerLimit\":4,\"inputOptions\":[{\"name\":\"pipelineDefaultEngine\",\"inputType\":\"Engine\",\"id\":\"b87c0c5d-a261-45ed-a428-b2b639d4ece4:input:1\",\"type\":\"Engine\",\"engineName\":\"149_Livy\",\"required\":true}],\"tasks\":[{\"children\":[\"DataflowTknup\"],\"iteratee\":{},\"id\":\"Terminator\",\"type\":\"Terminator\"},{\"parent\":[\"Terminator\"],\"stopOnTaskFailure\":\"N\",\"stopOnTaskSuccess\":\"N\",\"dfName\":\" cassandranormal\",\"stopDependentTasks\":\"N\",\"label\":\"Data\",\"type\":\"runDataFlow\",\"dfKey\":\"f0417a55-3b58-476e-aa33-2f4415d55385\",\"livyServer\":\"${pipelineDefaultEngine}\",\"children\":[],\"iteratee\":{},\"name\":\" cassandranormal\",\"id\":\"DataflowTknup\",\"parameters\":\"{\\\"limit_rows\\\":\\\"limit 1000\\\"}\"}]}"}