{"pipelineKey":"94b61f5a-dd6d-4b8e-8e52-385219401b3a","name":"Pipeline_621","description":"","definition":"{\"workerLimit\":4,\"inputOptions\":[{\"name\":\"pipelineDefaultEngine\",\"inputType\":\"Engine\",\"id\":\"32d632d6-7f25-4f46-9d50-7bd07fce54a5:input:1\",\"type\":\"string\",\"engineName\":\"146_livy\",\"required\":true}],\"selectedEngine\":\"135livy\",\"tasks\":[{\"children\":[\"DataflowUmQ0t\"],\"iteratee\":{},\"id\":\"Terminator\",\"type\":\"Terminator\"},{\"parent\":[\"Terminator\"],\"stopOnTaskFailure\":\"N\",\"dfName\":\" cassandranormal_Copy\",\"stopDependentTasks\":\"N\",\"label\":\"Data\",\"type\":\"runDataFlow\",\"dfKey\":\"41c11022-a005-4e2f-9071-24d1f791543b\",\"livyServer\":\"${pipelineDefaultEngine}\",\"children\":[],\"iteratee\":{},\"name\":\" cassandranormal_Copy\",\"id\":\"DataflowUmQ0t\",\"parameters\":\"limit_rows:limit 1000\"}]}"}