{"pipelineKey":"a2f902b9-ce06-477f-b4d5-13b1b47a730e","name":"Pipeline_fail","description":"","definition":"{\"workerLimit\":4,\"tasks\":[{\"children\":[\"DataflowspJLc\"],\"iteratee\":{},\"id\":\"Terminator\",\"type\":\"Terminator\"},{\"parent\":[\"Terminator\"],\"stopOnTaskFailure\":\"N\",\"dfName\":\"Dataflow_Fail_PL\",\"stopDependentTasks\":\"N\",\"label\":\"Data\",\"type\":\"runDataFlow\",\"dfKey\":\"3ae18e73-0824-4e9f-8070-1c383eb81b67\",\"livyServer\":\"146_livy\",\"children\":[],\"iteratee\":{},\"name\":\"Dataflow_Fail_PL\",\"id\":\"DataflowspJLc\",\"parameters\":\"limit_rows:limit 1000\"}]}"}