{"pipelineKey":"a21e1b908c07431f8d3a6d0b9dda4ed0","name":"Pipeline_1923","description":"","definition":"{\"workerLimit\":4,\"tasks\":[{\"children\":[\"Dataflows4L19\"],\"iteratee\":{},\"id\":\"Terminator\",\"type\":\"Terminator\"},{\"parent\":[\"Terminator\"],\"stopOnTaskFailure\":\"N\",\"dfName\":\"Dataflow_2595\",\"stopDependentTasks\":\"N\",\"label\":\"Data\",\"type\":\"runDataFlow\",\"userId\":\"86\",\"dfKey\":\"5c212867-c5b9-4609-b386-a3a1a50c4b2c\",\"livyServer\":\"168_new\",\"children\":[],\"iteratee\":{},\"name\":\"Dataflow_2595\",\"id\":\"Dataflows4L19\",\"parameters\":\"limit_rows:limit 1000\"}]}"}